README.md
setup.py
deezer_asy/DeezerAsy.py
deezer_asy/__init__.py
deezer_asy/aiodeezer.py
deezer_asy/exceptions.py
deezer_asy/util.py
deezer_asy/constants/__init__.py
deezer_asy/constants/api_methods.py
deezer_asy/constants/api_urls.py
deezer_asy/constants/image_hosts.py
deezer_asy/constants/networking_settings.py
deezer_asy/constants/search_types.py
deezer_asy/constants/track_formats.py
pydeezer_asy.egg-info/PKG-INFO
pydeezer_asy.egg-info/SOURCES.txt
pydeezer_asy.egg-info/dependency_links.txt
pydeezer_asy.egg-info/requires.txt
pydeezer_asy.egg-info/top_level.txt