Metadata-Version: 2.1
Name: pydeezer-asy
Version: 2.2.6
Summary: Asynchronous version of the `py-deezer` module
Home-page: https://github.com/drhspfn/deezer-asy
Author: drhspfn
Author-email: drhspfn@gmail.com
Classifier: Programming Language :: Python :: 3
Classifier: Operating System :: OS Independent
